microcosm_secretsmanager/__init__.py
microcosm_secretsmanager/loaders/__init__.py
microcosm_secretsmanager/loaders/base.py
microcosm_secretsmanager/loaders/conventions.py
microcosm_secretsmanager/loaders/loaders.py
microcosm_secretsmanager-2.0.0.dist-info/LICENSE
microcosm_secretsmanager-2.0.0.dist-info/METADATA
microcosm_secretsmanager-2.0.0.dist-info/WHEEL
microcosm_secretsmanager-2.0.0.dist-info/top_level.txt
microcosm_secretsmanager-2.0.0.dist-info/RECORD
